<?xml version="1.0" encoding="UTF-8"?>
<tv generator-info-name="WebGrab+Plus/w MDB &amp; REX Postprocess -- version V1.56.27 -- Jan van Straaten" generator-info-url="http://www.webgrabplus.com">
  <channel id="BS200(BS10) ?????????">
    <display-name lang="ja">BS200(BS10) ?????????</display-name>
    <url>http://www.skyperfect.co.jp</url>
  </channel>
  <channel id="BS201 ?????????">
    <display-name lang="ja">BS201 ?????????</display-name>
    <url>http://www.skyperfect.co.jp</url>
  </channel>
  <channel id="BS202 ?????????">
    <display-name lang="ja">BS202 ?????????</display-name>
    <url>http://www.skyperfect.co.jp</url>
  </channel>
  <channel id="CS218 ???????">
    <display-name lang="ja">CS218 ???????</display-name>
    <url>http://www.skyperfect.co.jp</url>
  </channel>
  <channel id="CS219 ????">
    <display-name lang="ja">CS219 ????</display-name>
    <url>http://www.skyperfect.co.jp</url>
  </channel>
  <channel id="CS223 ????????NECO">
    <display-name lang="ja">CS223 ????????NECO</display-name>
    <url>http://www.skyperfect.co.jp</url>
  </channel>
  <channel id="CS227 ?????">
    <display-name lang="ja">CS227 ?????</display-name>
    <url>http://www.skyperfect.co.jp</url>
  </channel>
  <channel id="CS240 ???????HD">
    <display-name lang="ja">CS240 ???????HD</display-name>
    <url>http://www.skyperfect.co.jp</url>
  </channel>
  <channel id="BS252 ?????????">
    <display-name lang="ja">BS252 ?????????</display-name>
    <url>http://www.skyperfect.co.jp</url>
  </channel>
  <channel id="BS255 ?????????????">
    <display-name lang="ja">BS255 ?????????????</display-name>
    <url>http://www.skyperfect.co.jp</url>
  </channel>
  <channel id="BS242 J SPORTS 1">
    <display-name lang="ja">BS242 J SPORTS 1</display-name>
    <url>http://www.skyperfect.co.jp</url>
  </channel>
  <channel id="BS243 J SPORTS 2">
    <display-name lang="ja">BS243 J SPORTS 2</display-name>
    <url>http://www.skyperfect.co.jp</url>
  </channel>
  <channel id="BS244 J SPORTS 3">
    <display-name lang="ja">BS244 J SPORTS 3</display-name>
    <url>http://www.skyperfect.co.jp</url>
  </channel>
  <channel id="BS245 J SPORTS 4">
    <display-name lang="ja">BS245 J SPORTS 4</display-name>
    <url>http://www.skyperfect.co.jp</url>
  </channel>
  <programme start="20170513094500 +0900" stop="20170513114500 +0900" channel="BS200(BS10) ?????????">
    <title lang="ja">[?][SS]X?????? (?)</title>
    <credits>
      <actor>????</actor>
      <actor>????/???</actor>
      <actor>?????/???</actor>
      <actor>????/????</actor>
      <actor>???/??</actor>
      <actor>???????</actor>
    </credits>
    <country>?????</country>
  </programme>
  <programme start="20170513114500 +0900" stop="20170513134200 +0900" channel="BS200(BS10) ?????????">
    <title lang="ja">[?][SS]???????? (?)</title>
    <credits>
      <actor>?????????</actor>
      <actor>???????/??????</actor>
      <actor>??????/??????</actor>
      <actor>???????/?????</actor>
      <actor>????/???</actor>
      <actor>???</actor>
    </credits>
    <country>?</country>
  </programme>
  <programme start="20170513134200 +0900" stop="20170513140000 +0900" channel="BS200(BS10) ?????????">
    <title lang="ja">[?]3????!???????10!????????Vol.2 (?)</title>
  </programme>
  <programme start="20170513140000 +0900" stop="20170513154100 +0900" channel="BS200(BS10) ?????????">
    <title lang="ja">[?][SS]??????????? (?)</title>
    <credits>
      <actor>????</actor>
      <actor>?????/????</actor>
      <actor>????/?????</actor>
      <actor>?????/???</actor>
      <actor>????/?????</actor>
      <actor>??</actor>
    </credits>
    <country>?</country>
  </programme>
  <programme start="20170513154100 +0900" stop="20170513160000 +0900" channel="BS200(BS10) ?????????">
    <title lang="ja">[?]??100??!???????/?????????????? (?)</title>
  </programme>
  <programme start="20170513160000 +0900" stop="20170513175400 +0900" channel="BS200(BS10) ?????????">
    <title lang="ja">[?][SS]??? (?)</title>
    <credits>
      <actor>???</actor>
      <actor>?????/?????</actor>
      <actor>?????/??</actor>
      <actor>????????/??</actor>
      <actor>????/?????</actor>
      <actor>??????</actor>
    </credits>
    <country>?</country>
  </programme>
  <programme start="20170513175400 +0900" stop="20170513181500 +0900" channel="BS200(BS10) ?????????">
    <title lang="ja">[?]?????????????????5/15???????????! (?)</title>
  </programme>
  <programme start="20170513181500 +0900" stop="20170513203100 +0900" channel="BS200(BS10) ?????????">
    <title lang="ja">?????[?][SS]????????????? (?)</title>
    <credits>
      <actor>???</actor>
      <actor>?????/?????</actor>
      <actor>?????/?????</actor>
      <actor>????/?????</actor>
      <actor>???/????</actor>
      <actor>??????</actor>
    </credits>
    <country>?????</country>
  </programme>
  <programme start="20170513203100 +0900" stop="20170513204500 +0900" channel="BS200(BS10) ?????????">
    <title lang="ja">[?]STAR1???????????9????????????9? (?)</title>
  </programme>
  <programme start="20170513204500 +0900" stop="20170513210000 +0900" channel="BS200(BS10) ?????????">
    <title lang="ja">[?]?????????EYES (?)</title>
  </programme>
  <programme start="20170513210000 +0900" stop="20170513225300 +0900" channel="BS200(BS10) ?????????">
    <title lang="ja">?????[?][SS]????:REBORN (?)</title>
    <credits>
      <actor>???????</actor>
      <actor>???????/?????</actor>
      <actor>???/?????</actor>
      <actor>L</actor>
      <actor>?????/?????</actor>
      <actor>????/??</actor>
      <actor>???????</actor>
    </credits>
    <country>???????</country>
  </programme>
  <programme start="20170513225300 +0900" stop="20170513230000 +0900" channel="BS200(BS10) ?????????">
    <title lang="ja">[?]??300??!?????????????????????????? (?)</title>
  </programme>
  <programme start="20170513090000 +0900" stop="20170513104500 +0900" channel="BS201 ?????????">
    <title lang="ja">[?]????????? (?)</title>
    <credits>
      <actor>???</actor>
      <actor>????/????</actor>
      <actor>????????/??????</actor>
      <actor>????/?????</actor>
      <actor>????????/??</actor>
      <actor>???</actor>
    </credits>
    <country>?</country>
  </programme>
  <programme start="20170513104500 +0900" stop="20170513124500 +0900" channel="BS201 ?????????">
    <title lang="ja">[?]????????????[??????????] (?)</title>
    <credits>
      <actor>??????</actor>
      <actor>?????/???</actor>
      <actor>??/??????</actor>
      <actor>?????/???</actor>
      <actor>????/????</actor>
      <actor>???</actor>
    </credits>
    <country>?</country>
  </programme>
  <programme start="20170513124500 +0900" stop="20170513150000 +0900" channel="BS201 ?????????">
    <title lang="ja">[?][SS]???????? (?)</title>
    <credits>
      <actor>????</actor>
      <actor>?????/?????</actor>
      <actor>?????/?????</actor>
      <actor>??/??????</actor>
      <actor>??????/????</actor>
      <actor>????</actor>
    </credits>
    <country>?</country>
  </programme>
  <programme start="20170513150000 +0900" stop="20170513170000 +0900" channel="BS201 ?????????">
    <title lang="ja">[?]??????? (?)</title>
    <credits>
      <actor>??????</actor>
      <actor>??????/???</actor>
      <actor>?????/????</actor>
      <actor>????/???</actor>
      <actor>???/????</actor>
      <actor>????=?????</actor>
    </credits>
    <country>?</country>
  </programme>
  <programme start="20170513170000 +0900" stop="20170513190000 +0900" channel="BS201 ?????????">
    <title lang="ja">[?][SS]??????? (?)</title>
    <credits>
      <actor>?????</actor>
      <actor>???/??????</actor>
      <actor>??????/????</actor>
      <actor>???????/???</actor>
      <actor>?????/????</actor>
      <actor>?????</actor>
    </credits>
    <country>???</country>
  </programme>
  <programme start="20170513190000 +0900" stop="20170513203800 +0900" channel="BS201 ?????????">
    <title lang="ja">[?][SS]??????????? (?)</title>
    <credits>
      <actor>????</actor>
      <actor>???????/??????</actor>
      <actor>??????/??</actor>
      <actor>????/????</actor>
      <actor>????/???</actor>
      <actor>?????</actor>
    </credits>
    <country>?????</country>
  </programme>
  <programme start="20170513203800 +0900" stop="20170513210000 +0900" channel="BS201 ?????????">
    <title lang="ja">[?]STAR2??????????9???THE?????? (?)</title>
  </programme>
  <programme start="20170513210000 +0900" stop="20170513230000 +0900" channel="BS201 ?????????">
    <title lang="ja">[?][SS]????!???? (?)</title>
    <credits>
      <actor>?????</actor>
      <actor>????/????</actor>
      <actor>????/???</actor>
      <actor>???/?????</actor>
      <actor>???</actor>
      <actor>????/????</actor>
      <actor>???</actor>
      <actor>???</actor>
    </credits>
    <country>?</country>
  </programme>
  <programme start="20170513094000 +0900" stop="20170513123000 +0900" channel="BS202 ?????????">
    <title lang="ja">[?][SS][?]????? vs ????????????????[?] (?)</title>
    <credits>
      <actor>??</actor>
      <actor>?????(????)/????</actor>
      <actor>????(????)/????</actor>
      <actor>????(????)/????</actor>
      <actor>???????(????)/????</actor>
      <actor>???(????)</actor>
    </credits>
    <country>?</country>
  </programme>
  <programme start="20170513123000 +0900" stop="20170513143000 +0900" channel="BS202 ?????????">
    <title lang="ja">?????[?][SS]???????[?] (?)</title>
    <credits>
      <actor>???</actor>
      <actor>??????(????)/????</actor>
      <actor>?????(?????)/?????</actor>
      <actor>?????(????)/???</actor>
      <actor>????(????)/????</actor>
      <actor>???(????)</actor>
    </credits>
    <country>??????</country>
  </programme>
  <programme start="20170513143000 +0900" stop="20170513164000 +0900" channel="BS202 ?????????">
    <title lang="ja">[?]??????????????[?] (?)</title>
    <credits>
      <actor>???</actor>
      <actor>?????(????)/??????</actor>
      <actor>??????(???)/??</actor>
      <actor>?????(????)/?????</actor>
      <actor>?????(????)/???</actor>
      <actor>?????(????)</actor>
    </credits>
    <country>?</country>
  </programme>
  <programme start="20170513164000 +0900" stop="20170513165000 +0900" channel="BS202 ?????????">
    <title lang="ja">[?]IN?FOCUS&lt;?????????????&gt; (?)</title>
  </programme>
  <programme start="20170513165000 +0900" stop="20170513190000 +0900" channel="BS202 ?????????">
    <title lang="ja">[?][SS][?]?????????????[?] (?)</title>
    <credits>
      <actor>????</actor>
      <actor>???(???)/???</actor>
      <actor>???(????)/?????</actor>
      <actor>??(????/??)/????</actor>
      <actor>B</actor>
      <actor>?????(?????)/???</actor>
      <actor>???(????)</actor>
    </credits>
    <country>?</country>
  </programme>
  <programme start="20170513190000 +0900" stop="20170513204400 +0900" channel="BS202 ?????????">
    <title lang="ja">[?]????????[?] (?)</title>
    <credits>
      <actor>????</actor>
      <actor>????(?????)/????</actor>
      <actor>????(?????)/????</actor>
      <actor>???(?????)/???</actor>
      <actor>?????(???)/????</actor>
      <actor>??</actor>
      <actor>????(????)</actor>
    </credits>
    <country>?</country>
  </programme>
  <programme start="20170513204400 +0900" stop="20170513210000 +0900" channel="BS202 ?????????">
    <title lang="ja">[?]STAR3??????????9????????????????? (?)</title>
  </programme>
  <programme start="20170513210000 +0900" stop="20170513231000 +0900" channel="BS202 ?????????">
    <title lang="ja">[?][SS]????????[?] (?)</title>
    <credits>
      <actor>?????</actor>
      <actor>?????(???)/???</actor>
      <actor>?????(????)/?????</actor>
      <actor>???(???)/?????</actor>
      <actor>????</actor>
      <actor>?????????(????)/?????</actor>
      <actor>?</actor>
      <actor>?????(?????)</actor>
    </credits>
    <country>?</country>
  </programme>
  <programme start="20170513100000 +0900" stop="20170513110000 +0900" channel="CS218 ???????">
    <title lang="ja">?? season6 #3 (?)</title>
    <credits>
      <actor>???????????????????????
2007??19?</actor>
    </credits>
  </programme>
  <programme start="20170513110000 +0900" stop="20170513123000 +0900" channel="CS218 ???????">
    <title lang="ja">????? (?)</title>
    <credits>
      <actor>?????????????????????????????????
??:??????:?????????
1958?85?</actor>
    </credits>
  </programme>
  <programme start="20170513123000 +0900" stop="20170513143000 +0900" channel="CS218 ???????">
    <title lang="ja">???????? (?)</title>
  </programme>
  <programme start="20170513143000 +0900" stop="20170513160000 +0900" channel="CS218 ???????">
    <title lang="ja">???????? (?)</title>
  </programme>
  <programme start="20170513160000 +0900" stop="20170513175000 +0900" channel="CS218 ???????">
    <title lang="ja">???????? (?)</title>
    <credits>
      <actor>?????????????????????????????????
??:??????:???
2006?93?</actor>
    </credits>
  </programme>
  <programme start="20170513175000 +0900" stop="20170513180000 +0900" channel="CS218 ???????">
    <title lang="ja">[?]???? (?)</title>
  </programme>
  <programme start="20170513180000 +0900" stop="20170513195000 +0900" channel="CS218 ???????">
    <title lang="ja">??????????? (?)</title>
    <credits>
      <actor>???????????????????????????????????
??:???????:????
1959?92?</actor>
    </credits>
  </programme>
  <programme start="20170513195000 +0900" stop="20170513200000 +0900" channel="CS218 ???????">
    <title lang="ja">[?]Coming Soon (?)</title>
  </programme>
  <programme start="20170513200000 +0900" stop="20170513222000 +0900" channel="CS218 ???????">
    <title lang="ja">??????? (?)</title>
  </programme>
  <programme start="20170513222000 +0900" stop="20170513223000 +0900" channel="CS218 ???????">
    <title lang="ja">????!?????????? (?)</title>
  </programme>
  <programme start="20170513091500 +0900" stop="20170513110000 +0900" channel="CS219 ????">
    <title lang="ja">???????????????????????? (?)</title>
  </programme>
  <programme start="20170513110000 +0900" stop="20170513120000 +0900" channel="CS219 ????">
    <title lang="ja">[?]?????? ????2?13???? ????????????????? (?)</title>
  </programme>
  <programme start="20170513120000 +0900" stop="20170513130000 +0900" channel="CS219 ????">
    <title lang="ja">[?]?????? ????2?14???? ????????????????? (?)</title>
  </programme>
  <programme start="20170513130000 +0900" stop="20170513140000 +0900" channel="CS219 ????">
    <title lang="ja">[?][?]?????????????7??????? (?)</title>
  </programme>
  <programme start="20170513140000 +0900" stop="20170513150000 +0900" channel="CS219 ????">
    <title lang="ja">[?][?]?????????????8??????? (?)</title>
  </programme>
  <programme start="20170513150000 +0900" stop="20170513170000 +0900" channel="CS219 ????">
    <title lang="ja">?????????????????? (?)</title>
  </programme>
  <programme start="20170513170000 +0900" stop="20170513191500 +0900" channel="CS219 ????">
    <title lang="ja">???????????????? (?)</title>
  </programme>
  <programme start="20170513191500 +0900" stop="20170513210000 +0900" channel="CS219 ????">
    <title lang="ja">???????????????? (?)</title>
  </programme>
  <programme start="20170513210000 +0900" stop="20170513224500 +0900" channel="CS219 ????">
    <title lang="ja">?????? ???????????? (?)</title>
  </programme>
  <programme start="20170513224500 +0900" stop="20170513230000 +0900" channel="CS219 ????">
    <title lang="ja">[?]???? (?)</title>
  </programme>
  <programme start="20170513100000 +0900" stop="20170513103000 +0900" channel="CS223 ????????NECO">
    <title lang="ja">[?]???1/2?OVA??????????????????????????????? (?)</title>
  </programme>
  <programme start="20170513103000 +0900" stop="20170513123000 +0900" channel="CS223 ????????NECO">
    <title lang="ja">????????????27?????????????????? (?)</title>
  </programme>
  <programme start="20170513123000 +0900" stop="20170513144000 +0900" channel="CS223 ????????NECO">
    <title lang="ja">????????-THE FIRST LOVE &amp; THE LAST KILL- (?)</title>
  </programme>
  <programme start="20170513144000 +0900" stop="20170513151000 +0900" channel="CS223 ????????NECO">
    <title lang="ja">????????? (?)</title>
  </programme>
  <programme start="20170513151000 +0900" stop="20170513165000 +0900" channel="CS223 ????????NECO">
    <title lang="ja">????????12??????????????? (?)</title>
  </programme>
  <programme start="20170513165000 +0900" stop="20170513182000 +0900" channel="CS223 ????????NECO">
    <title lang="ja">????????13?????????????? (?)</title>
  </programme>
  <programme start="20170513182000 +0900" stop="20170513185000 +0900" channel="CS223 ????????NECO">
    <title lang="ja">????????? (?)</title>
  </programme>
  <programme start="20170513185000 +0900" stop="20170513185500 +0900" channel="CS223 ????????NECO">
    <title lang="ja">??????????????????? (?)</title>
  </programme>
  <programme start="20170513185500 +0900" stop="20170513210000 +0900" channel="CS223 ????????NECO">
    <title lang="ja">?????????????????????????????????????? (?)</title>
  </programme>
  <programme start="20170513210000 +0900" stop="20170513234000 +0900" channel="CS223 ????????NECO">
    <title lang="ja">?????????? (?)</title>
  </programme>
  <programme start="20170513081500 +0900" stop="20170513110000 +0900" channel="CS227 ?????">
    <title lang="ja">???? (?)</title>
    <country>??</country>
  </programme>
  <programme start="20170513110000 +0900" stop="20170513130000 +0900" channel="CS227 ?????">
    <title lang="ja">????????????????????? (?)</title>
    <country>????</country>
  </programme>
  <programme start="20170513130000 +0900" stop="20170513150000 +0900" channel="CS227 ?????">
    <title lang="ja">??????????? (?)</title>
    <country>????</country>
  </programme>
  <programme start="20170513150000 +0900" stop="20170513170000 +0900" channel="CS227 ?????">
    <title lang="ja">??????????1990? (?)</title>
    <country>????</country>
  </programme>
  <programme start="20170513170000 +0900" stop="20170513184500 +0900" channel="CS227 ?????">
    <title lang="ja">??? (?)</title>
    <country>????</country>
  </programme>
  <programme start="20170513184500 +0900" stop="20170513205500 +0900" channel="CS227 ?????">
    <title lang="ja">??????????????????? (?)</title>
    <country>???</country>
  </programme>
  <programme start="20170513205500 +0900" stop="20170513210000 +0900" channel="CS227 ?????">
    <title lang="ja">???????????????? (?)</title>
  </programme>
  <programme start="20170513210000 +0900" stop="20170513230000 +0900" channel="CS227 ?????">
    <title lang="ja">????????????????? (?)</title>
    <country>????</country>
  </programme>
  <programme start="20170513084500 +0900" stop="20170513104500 +0900" channel="CS240 ???????HD">
    <title lang="ja">?????????? ??? ??????? (?)</title>
    <country>????</country>
  </programme>
  <programme start="20170513104500 +0900" stop="20170513110000 +0900" channel="CS240 ???????HD">
    <title lang="ja">??????????? (?)</title>
  </programme>
  <programme start="20170513110000 +0900" stop="20170513124500 +0900" channel="CS240 ???????HD">
    <title lang="ja">???????????????? (?)</title>
    <country>???</country>
  </programme>
  <programme start="20170513124500 +0900" stop="20170513143000 +0900" channel="CS240 ???????HD">
    <title lang="ja">??????????????????? (?)</title>
    <country>???</country>
  </programme>
  <programme start="20170513143000 +0900" stop="20170513161500 +0900" channel="CS240 ???????HD">
    <title lang="ja">???????VS????????????????? (?)</title>
    <country>????</country>
  </programme>
  <programme start="20170513161500 +0900" stop="20170513183000 +0900" channel="CS240 ???????HD">
    <title lang="ja">????????????? (?)</title>
    <country>???</country>
  </programme>
  <programme start="20170513183000 +0900" stop="20170513205000 +0900" channel="CS240 ???????HD">
    <title lang="ja">????????????? (?)</title>
    <country>????</country>
  </programme>
  <programme start="20170513205000 +0900" stop="20170513205500 +0900" channel="CS240 ???????HD">
    <title lang="ja">???????????? (?)</title>
  </programme>
  <programme start="20170513205500 +0900" stop="20170513210000 +0900" channel="CS240 ???????HD">
    <title lang="ja">??????? (?)</title>
  </programme>
  <programme start="20170513210000 +0900" stop="20170513232500 +0900" channel="CS240 ???????HD">
    <title lang="ja">????????????? (?)</title>
    <country>????</country>
  </programme>
  <programme start="20170513232500 +0900" stop="20170513233000 +0900" channel="CS240 ???????HD">
    <title lang="ja">???????????? (?)</title>
  </programme>
  <programme start="20170513100000 +0900" stop="20170513120000 +0900" channel="BS252 ?????????">
    <title lang="ja">[?]??????? (?)</title>
    <country>????</country>
  </programme>
  <programme start="20170513120000 +0900" stop="20170513141500 +0900" channel="BS252 ?????????">
    <title lang="ja">?5.1?[?]??????? [???] (?)</title>
    <country>????</country>
  </programme>
  <programme start="20170513141500 +0900" stop="20170513170000 +0900" channel="BS252 ?????????">
    <title lang="ja">?5.1?[?]???????2??? [???] (?)</title>
    <country>????</country>
  </programme>
  <programme start="20170513170000 +0900" stop="20170513190000 +0900" channel="BS252 ?????????">
    <title lang="ja">[?]????????????? (?)</title>
    <country>????</country>
  </programme>
  <programme start="20170513190000 +0900" stop="20170513210000 +0900" channel="BS252 ?????????">
    <title lang="ja">[?]???????? (?)</title>
    <country>????</country>
  </programme>
  <programme start="20170513210000 +0900" stop="20170513231500 +0900" channel="BS252 ?????????">
    <title lang="ja">?5.1?[?]???????13???? (?)</title>
    <country>???</country>
  </programme>
  <programme start="20170513083000 +0900" stop="20170513102000 +0900" channel="BS255 ?????????????">
    <title lang="ja">?????????????????????????????? (?)</title>
  </programme>
  <programme start="20170513102000 +0900" stop="20170513124000 +0900" channel="BS255 ?????????????">
    <title lang="ja">??????????????????????????????? (?)</title>
  </programme>
  <programme start="20170513124000 +0900" stop="20170513150000 +0900" channel="BS255 ?????????????">
    <title lang="ja">???????????????????????????????? (?)</title>
  </programme>
  <programme start="20170513150000 +0900" stop="20170513151000 +0900" channel="BS255 ?????????????">
    <title lang="ja">??????????????????? (?)</title>
  </programme>
  <programme start="20170513151000 +0900" stop="20170513172000 +0900" channel="BS255 ?????????????">
    <title lang="ja">?????????????????????? (?)</title>
  </programme>
  <programme start="20170513172000 +0900" stop="20170513192000 +0900" channel="BS255 ?????????????">
    <title lang="ja">??????????????????????????????? (?)</title>
  </programme>
  <programme start="20170513192000 +0900" stop="20170513210000 +0900" channel="BS255 ?????????????">
    <title lang="ja">???? #2???????????????????????? (?)</title>
  </programme>
  <programme start="20170513210000 +0900" stop="20170513231000 +0900" channel="BS255 ?????????????">
    <title lang="ja">????????? ??????????????????????? (?)</title>
  </programme>
  <programme start="20170513083000 +0900" stop="20170513120000 +0900" channel="BS242 J SPORTS 1">
    <title lang="ja">????2017 ?????(5/12) (?)</title>
  </programme>
  <programme start="20170513120000 +0900" stop="20170513121500 +0900" channel="BS242 J SPORTS 1">
    <title lang="ja">??????????2017 ???????1? ??????? (?)</title>
  </programme>
  <programme start="20170513121500 +0900" stop="20170513125000 +0900" channel="BS242 J SPORTS 1">
    <title lang="ja">????????#23 (?)</title>
  </programme>
  <programme start="20170513125000 +0900" stop="20170513140000 +0900" channel="BS242 J SPORTS 1">
    <title lang="ja">??????????????? ??????????????????2017 ?2? (?)</title>
  </programme>
  <programme start="20170513140000 +0900" stop="20170513160000 +0900" channel="BS242 J SPORTS 1">
    <title lang="ja">???? Presents?66??????????? ?? ????????? (?)</title>
  </programme>
  <programme start="20170513160000 +0900" stop="20170513183000 +0900" channel="BS242 J SPORTS 1">
    <title lang="ja">[?]B??? 2016-17 ????????? ???? ?1?? ????? (?)</title>
  </programme>
  <programme start="20170513183000 +0900" stop="20170513194000 +0900" channel="BS242 J SPORTS 1">
    <title lang="ja">FIM ?????????????2017 ?4? ????(????) (?)</title>
  </programme>
  <programme start="20170513194000 +0900" stop="20170513214000 +0900" channel="BS242 J SPORTS 1">
    <title lang="ja">????????????????2017 ?????(5/13) (?)</title>
  </programme>
  <programme start="20170513214000 +0900" stop="20170513215500 +0900" channel="BS242 J SPORTS 1">
    <title lang="ja">??????????2017 ???????1? ??????? (?)</title>
  </programme>
  <programme start="20170513080000 +0900" stop="20170513120000 +0900" channel="BS243 J SPORTS 2">
    <title lang="ja">[?]?????????2017 ???????????(5/12) (?)</title>
  </programme>
  <programme start="20170513120000 +0900" stop="20170513130000 +0900" channel="BS243 J SPORTS 2">
    <title lang="ja">???? ??????? ????? #36 (?)</title>
  </programme>
  <programme start="20170513130000 +0900" stop="20170513143000 +0900" channel="BS243 J SPORTS 2">
    <title lang="ja">???????? The REAL ???? Sogakope Dreams ???????????? (?)</title>
  </programme>
  <programme start="20170513143000 +0900" stop="20170513145500 +0900" channel="BS243 J SPORTS 2">
    <title lang="ja">??????????2017 ???????1? ??????? (?)</title>
  </programme>
  <programme start="20170513145500 +0900" stop="20170513152500 +0900" channel="BS243 J SPORTS 2">
    <title lang="ja">????????????Foot?FRIDAY(5/12) (?)</title>
  </programme>
  <programme start="20170513152500 +0900" stop="20170513155500 +0900" channel="BS243 J SPORTS 2">
    <title lang="ja">????????#23 (?)</title>
  </programme>
  <programme start="20170513155500 +0900" stop="20170513165500 +0900" channel="BS243 J SPORTS 2">
    <title lang="ja">????????The REAL ??????? INS AND OUTS (?)</title>
  </programme>
  <programme start="20170513165500 +0900" stop="20170513193000 +0900" channel="BS243 J SPORTS 2">
    <title lang="ja">[?]????????????????2017 ?????(5/13) (?)</title>
  </programme>
  <programme start="20170513193000 +0900" stop="20170513200000 +0900" channel="BS243 J SPORTS 2">
    <title lang="ja">[??][?]BOOMER #85 ???????? (?)</title>
  </programme>
  <programme start="20170513200000 +0900" stop="20170513203000 +0900" channel="BS243 J SPORTS 2">
    <title lang="ja">???? ??????? ???????? #34 (?)</title>
  </programme>
  <programme start="20170513203000 +0900" stop="20170513220000 +0900" channel="BS243 J SPORTS 2">
    <title lang="ja">???????? The REAL ???? Sogakope Dreams ???????????? (?)</title>
  </programme>
  <programme start="20170513220000 +0900" stop="20170513222400 +0900" channel="BS243 J SPORTS 2">
    <title lang="ja">??????????2017 ???????1? ??????? (?)</title>
  </programme>
  <programme start="20170513063000 +0900" stop="20170513133000 +0900" channel="BS244 J SPORTS 3">
    <title lang="ja">FIA ???????(WEC) 2017 ?2? ???????????6?????(?? (?)</title>
  </programme>
  <programme start="20170513133000 +0900" stop="20170513180000 +0900" channel="BS244 J SPORTS 3">
    <title lang="ja">[?]????2017 ??????????(5/13) (?)</title>
  </programme>
  <programme start="20170513180000 +0900" stop="20170513190000 +0900" channel="BS244 J SPORTS 3">
    <title lang="ja">??????????????? ??????????????????2017 ?2? (?)</title>
  </programme>
  <programme start="20170513190000 +0900" stop="20170513200000 +0900" channel="BS244 J SPORTS 3">
    <title lang="ja">GTV2017 #2 ?SUPER GT ????????? (?)</title>
  </programme>
  <programme start="20170513200000 +0900" stop="20170513233000 +0900" channel="BS244 J SPORTS 3">
    <title lang="ja">?????????2017 ???????????(5/12) (?)</title>
  </programme>
  <programme start="20170513100000 +0900" stop="20170513110000 +0900" channel="BS245 J SPORTS 4">
    <title lang="ja">WWE ??????? ????? ????????? ?????#925 (?)</title>
  </programme>
  <programme start="20170513110000 +0900" stop="20170513130000 +0900" channel="BS245 J SPORTS 4">
    <title lang="ja">2017?????????ISU????????????????? #1 (?)</title>
  </programme>
  <programme start="20170513130000 +0900" stop="20170513134000 +0900" channel="BS245 J SPORTS 4">
    <title lang="ja">????????????2017 #16 ????????????? (?)</title>
  </programme>
  <programme start="20170513134000 +0900" stop="20170513155000 +0900" channel="BS245 J SPORTS 4">
    <title lang="ja">????????2017 ?12? ????????????(5/12) (?)</title>
  </programme>
  <programme start="20170513155000 +0900" stop="20170513162500 +0900" channel="BS245 J SPORTS 4">
    <title lang="ja">???????????? Mobil 1 The Grid 2017 #6 (?)</title>
  </programme>
  <programme start="20170513162500 +0900" stop="20170513184500 +0900" channel="BS245 J SPORTS 4">
    <title lang="ja">[?]????????2017 ?12? ???????(NZ)???????(NZ) (?)</title>
  </programme>
  <programme start="20170513184500 +0900" stop="20170513190000 +0900" channel="BS245 J SPORTS 4">
    <title lang="ja">??????????2017 ???????1? ??????? (?)</title>
  </programme>
  <programme start="20170513190000 +0900" stop="20170513200000 +0900" channel="BS245 J SPORTS 4">
    <title lang="ja">??????????????? ??????????????????2017 ?2? (?)</title>
  </programme>
  <programme start="20170513200000 +0900" stop="20170513202300 +0900" channel="BS245 J SPORTS 4">
    <title lang="ja">[??]2017 FIA ???????(WEC) ?? (?)</title>
  </programme>
  <programme start="20170513202300 +0900" stop="20170513230000 +0900" channel="BS245 J SPORTS 4">
    <title lang="ja">[?]???? ??????? ?37?-5 ???????C?????(????) (?)</title>
  </programme>
</tv>