<?xml version="1.0" encoding="UTF-8"?>
<tv generator-info-name="WebGrab+Plus/w MDB &amp; REX Postprocess -- version V1.56.27 -- Jan van Straaten" generator-info-url="http://www.webgrabplus.com">
  <channel id="BS200(BS10) ?????????">
    <display-name lang="ja">BS200(BS10) ?????????</display-name>
    <url>http://www.skyperfect.co.jp</url>
  </channel>
  <channel id="BS201 ?????????">
    <display-name lang="ja">BS201 ?????????</display-name>
    <url>http://www.skyperfect.co.jp</url>
  </channel>
  <channel id="BS202 ?????????">
    <display-name lang="ja">BS202 ?????????</display-name>
    <url>http://www.skyperfect.co.jp</url>
  </channel>
  <channel id="CS218 ???????">
    <display-name lang="ja">CS218 ???????</display-name>
    <url>http://www.skyperfect.co.jp</url>
  </channel>
  <channel id="CS219 ????">
    <display-name lang="ja">CS219 ????</display-name>
    <url>http://www.skyperfect.co.jp</url>
  </channel>
  <channel id="CS223 ????????NECO">
    <display-name lang="ja">CS223 ????????NECO</display-name>
    <url>http://www.skyperfect.co.jp</url>
  </channel>
  <channel id="CS227 ?????">
    <display-name lang="ja">CS227 ?????</display-name>
    <url>http://www.skyperfect.co.jp</url>
  </channel>
  <channel id="CS240 ???????HD">
    <display-name lang="ja">CS240 ???????HD</display-name>
    <url>http://www.skyperfect.co.jp</url>
  </channel>
  <channel id="BS252 ?????????">
    <display-name lang="ja">BS252 ?????????</display-name>
    <url>http://www.skyperfect.co.jp</url>
  </channel>
  <channel id="BS255 ?????????????">
    <display-name lang="ja">BS255 ?????????????</display-name>
    <url>http://www.skyperfect.co.jp</url>
  </channel>
  <channel id="BS242 J SPORTS 1">
    <display-name lang="ja">BS242 J SPORTS 1</display-name>
    <url>http://www.skyperfect.co.jp</url>
  </channel>
  <channel id="BS243 J SPORTS 2">
    <display-name lang="ja">BS243 J SPORTS 2</display-name>
    <url>http://www.skyperfect.co.jp</url>
  </channel>
  <channel id="BS244 J SPORTS 3">
    <display-name lang="ja">BS244 J SPORTS 3</display-name>
    <url>http://www.skyperfect.co.jp</url>
  </channel>
  <channel id="BS245 J SPORTS 4">
    <display-name lang="ja">BS245 J SPORTS 4</display-name>
    <url>http://www.skyperfect.co.jp</url>
  </channel>
  <programme start="20170521100000 +0900" stop="20170521113000 +0900" channel="BS200(BS10) ?????????">
    <title lang="ja">[SS]????????????#1 (?)</title>
    <credits>
      <actor>????</actor>
      <actor>?????=????/????</actor>
      <actor>?????/????</actor>
      <actor>????/????</actor>
      <actor>????/?????</actor>
      <actor>????</actor>
    </credits>
  </programme>
  <programme start="20170521113000 +0900" stop="20170521124000 +0900" channel="BS200(BS10) ?????????">
    <title lang="ja">[SS]TABOO?#4 (?)</title>
    <credits>
      <actor>??</actor>
      <actor>????/?????</actor>
      <actor>????/?????</actor>
      <actor>????/???</actor>
      <actor>??????/????</actor>
      <actor>?????</actor>
    </credits>
  </programme>
  <programme start="20170521124000 +0900" stop="20170521134000 +0900" channel="BS200(BS10) ?????????">
    <title lang="ja">[SS]????????????????/O?J?????????#8 (?)</title>
    <credits>
      <actor>????</actor>
      <actor>??????Jr./???</actor>
      <actor>??????/??</actor>
      <actor>?????/?????</actor>
      <actor>??????/?????</actor>
      <actor>B</actor>
      <actor>????</actor>
    </credits>
  </programme>
  <programme start="20170521134000 +0900" stop="20170521144000 +0900" channel="BS200(BS10) ?????????">
    <title lang="ja">[SS]???????????#9 (?)</title>
    <credits>
      <actor>????</actor>
      <actor>????/????</actor>
      <actor>?????/????</actor>
      <actor>???/????</actor>
      <actor>???/???</actor>
      <actor>??????</actor>
    </credits>
  </programme>
  <programme start="20170521144000 +0900" stop="20170521155000 +0900" channel="BS200(BS10) ?????????">
    <title lang="ja">[SS]????????????????:??????#3 (?)</title>
    <credits>
      <actor>????</actor>
      <actor>????/????</actor>
      <actor>???????/???</actor>
      <actor>?????/??</actor>
      <actor>???/????</actor>
      <actor>????=????</actor>
    </credits>
  </programme>
  <programme start="20170521155000 +0900" stop="20170521170000 +0900" channel="BS200(BS10) ?????????">
    <title lang="ja">[SS]????????????????:??????#4 (?)</title>
    <credits>
      <actor>????</actor>
      <actor>????/????</actor>
      <actor>???????/???</actor>
      <actor>?????/??</actor>
      <actor>???/????</actor>
      <actor>????=????</actor>
    </credits>
  </programme>
  <programme start="20170521170000 +0900" stop="20170521182300 +0900" channel="BS200(BS10) ?????????">
    <title lang="ja">[?][SS]???/?? (?)</title>
    <credits>
      <actor>???</actor>
      <actor>????/?????</actor>
      <actor>?????/???</actor>
      <actor>???/???????</actor>
      <actor>??????/???</actor>
      <actor>???</actor>
    </credits>
    <country>?</country>
  </programme>
  <programme start="20170521182300 +0900" stop="20170521184500 +0900" channel="BS200(BS10) ?????????">
    <title lang="ja">[?]???????????????6??????????! (?)</title>
  </programme>
  <programme start="20170521184500 +0900" stop="20170521203300 +0900" channel="BS200(BS10) ?????????">
    <title lang="ja">[?][SS]???????? (?)</title>
    <credits>
      <actor>?????</actor>
      <actor>?????/???</actor>
      <actor>?????/?????</actor>
      <actor>???/?????</actor>
      <actor>????</actor>
      <actor>?????????/?????</actor>
      <actor>?</actor>
      <actor>?????</actor>
    </credits>
    <country>?</country>
  </programme>
  <programme start="20170521203300 +0900" stop="20170521204500 +0900" channel="BS200(BS10) ?????????">
    <title lang="ja">[?]STAR1???????????9???STAR????? (?)</title>
  </programme>
  <programme start="20170521204500 +0900" stop="20170521210000 +0900" channel="BS200(BS10) ?????????">
    <title lang="ja">[?]?????????EYES (?)</title>
  </programme>
  <programme start="20170521210000 +0900" stop="20170521230000 +0900" channel="BS200(BS10) ?????????">
    <title lang="ja">?????[?][SS]??? (?)</title>
    <credits>
      <actor>???</actor>
      <actor>????/?????</actor>
      <actor>??????/????</actor>
      <actor>???/????</actor>
      <actor>??????/?????</actor>
      <actor>H</actor>
      <actor>????</actor>
    </credits>
    <country>??????????</country>
  </programme>
  <programme start="20170521230000 +0900" stop="20170521231500 +0900" channel="BS200(BS10) ?????????">
    <title lang="ja">[?]???????????7??????!(5/27) (?)</title>
  </programme>
  <programme start="20170521074000 +0900" stop="20170521101000 +0900" channel="BS201 ?????????">
    <title lang="ja">[?][SS]????/JFK??????? (?)</title>
    <credits>
      <actor>????</actor>
      <actor>?????/???</actor>
      <actor>?????/?????</actor>
      <actor>????/J</actor>
      <actor>T</actor>
      <actor>?????/???</actor>
      <actor>C</actor>
      <actor>????</actor>
    </credits>
    <country>?</country>
  </programme>
  <programme start="20170521101000 +0900" stop="20170521121000 +0900" channel="BS201 ?????????">
    <title lang="ja">[?][SS]?????????????? (?)</title>
    <credits>
      <actor>???</actor>
      <actor>?????/??????</actor>
      <actor>??????/??</actor>
      <actor>?????/?????</actor>
      <actor>?????/???</actor>
      <actor>?????</actor>
    </credits>
    <country>?</country>
  </programme>
  <programme start="20170521121000 +0900" stop="20170521140000 +0900" channel="BS201 ?????????">
    <title lang="ja">[?][SS]????????? (?)</title>
    <credits>
      <actor>????</actor>
      <actor>????/???</actor>
      <actor>????/???</actor>
      <actor>???/???</actor>
      <actor>?????/?????</actor>
      <actor>?????</actor>
    </credits>
    <country>?</country>
  </programme>
  <programme start="20170521140000 +0900" stop="20170521161500 +0900" channel="BS201 ?????????">
    <title lang="ja">[?]?????????/????? (?)</title>
    <credits>
      <actor>????</actor>
      <actor>?????/???</actor>
      <actor>?????????/????</actor>
      <actor>???????/???</actor>
      <actor>????/????</actor>
    </credits>
    <country>?</country>
  </programme>
  <programme start="20170521161500 +0900" stop="20170521183000 +0900" channel="BS201 ?????????">
    <title lang="ja">[?][SS]????????? (?)</title>
    <credits>
      <actor>?????</actor>
      <actor>??/????</actor>
      <actor>????/???</actor>
      <actor>????/?????</actor>
      <actor>???????/???</actor>
      <actor>??</actor>
      <actor>????</actor>
    </credits>
    <country>?</country>
  </programme>
  <programme start="20170521183000 +0900" stop="20170521203600 +0900" channel="BS201 ?????????">
    <title lang="ja">[?][SS]???????? (?)</title>
    <credits>
      <actor>?????</actor>
      <actor>??/???</actor>
      <actor>?????/???</actor>
      <actor>????Jr./?????</actor>
      <actor>???/????</actor>
      <actor>????</actor>
    </credits>
    <country>?</country>
  </programme>
  <programme start="20170521203600 +0900" stop="20170521210000 +0900" channel="BS201 ?????????">
    <title lang="ja">[?]??:????60?????53???????????????? (?)</title>
  </programme>
  <programme start="20170521210000 +0900" stop="20170521230000 +0900" channel="BS201 ?????????">
    <title lang="ja">[?]???? (?)</title>
    <credits>
      <actor>???</actor>
      <actor>???/????</actor>
      <actor>???/?????</actor>
      <actor>???/???</actor>
      <actor>???/?????</actor>
      <actor>??????</actor>
    </credits>
    <country>???</country>
  </programme>
  <programme start="20170521100000 +0900" stop="20170521115000 +0900" channel="BS202 ?????????">
    <title lang="ja">?????[?][SS][?]????????[?] (?)</title>
    <credits>
      <actor>???(???)/???(????)/????(??)/????(????)/?????(?????)</actor>
    </credits>
    <country>????????</country>
  </programme>
  <programme start="20170521115000 +0900" stop="20170521120000 +0900" channel="BS202 ?????????">
    <title lang="ja">[?]IN FOCUS&lt;?????:???????/?????????&gt; (?)</title>
  </programme>
  <programme start="20170521120000 +0900" stop="20170521142000 +0900" channel="BS202 ?????????">
    <title lang="ja">[?][SS][?]?????:???????/?????????[?] (?)</title>
    <credits>
      <actor>??</actor>
      <actor>????(????)/?????</actor>
      <actor>???(????)/????</actor>
      <actor>???(????)/????</actor>
      <actor>??????(?????)/????</actor>
      <actor>???(????)</actor>
    </credits>
    <country>???</country>
  </programme>
  <programme start="20170521142000 +0900" stop="20170521163000 +0900" channel="BS202 ?????????">
    <title lang="ja">[?]E.T.[20????????????][?] (?)</title>
    <credits>
      <actor>????</actor>
      <actor>????(????)/????</actor>
      <actor>????(???)/????</actor>
      <actor>????(???)/???</actor>
      <actor>????(????)/????</actor>
      <actor>??????(??)</actor>
    </credits>
    <country>?</country>
  </programme>
  <programme start="20170521163000 +0900" stop="20170521164000 +0900" channel="BS202 ?????????">
    <title lang="ja">[?]IN FOCUS&lt;?????&gt; (?)</title>
  </programme>
  <programme start="20170521164000 +0900" stop="20170521185000 +0900" channel="BS202 ?????????">
    <title lang="ja">[?][SS]?????[?] (?)</title>
    <credits>
      <actor>???</actor>
      <actor>???(????)/????????</actor>
      <actor>???(????)/???</actor>
      <actor>????(???)/???</actor>
      <actor>??????(????)/????</actor>
      <actor>????(????)</actor>
    </credits>
    <country>?</country>
  </programme>
  <programme start="20170521185000 +0900" stop="20170521190000 +0900" channel="BS202 ?????????">
    <title lang="ja">[?]IN FOCUS&lt;????????&gt; (?)</title>
  </programme>
  <programme start="20170521190000 +0900" stop="20170521204100 +0900" channel="BS202 ?????????">
    <title lang="ja">[?][SS]????????[?] (?)</title>
    <credits>
      <actor>????</actor>
      <actor>?????(????)/????</actor>
      <actor>????(????)/????</actor>
      <actor>?????(????)/????</actor>
      <actor>????(???)/?????</actor>
      <actor>???(?????)</actor>
    </credits>
    <country>?</country>
  </programme>
  <programme start="20170521204100 +0900" stop="20170521210000 +0900" channel="BS202 ?????????">
    <title lang="ja">[?]STAR3???????????????????9? (?)</title>
  </programme>
  <programme start="20170521100000 +0900" stop="20170521110000 +0900" channel="CS218 ???????">
    <title lang="ja">??????????? #10 (?)</title>
  </programme>
  <programme start="20170521110000 +0900" stop="20170521120000 +0900" channel="CS218 ???????">
    <title lang="ja">??????????? #11 (?)</title>
  </programme>
  <programme start="20170521120000 +0900" stop="20170521150000 +0900" channel="CS218 ???????">
    <title lang="ja">????????? ?????????&amp;???????????? (?)</title>
    <credits>
      <actor>???????????????????????
??:????
2011?179?</actor>
    </credits>
  </programme>
  <programme start="20170521150000 +0900" stop="20170521155000 +0900" channel="CS218 ???????">
    <title lang="ja">???????????? (?)</title>
  </programme>
  <programme start="20170521155000 +0900" stop="20170521160000 +0900" channel="CS218 ???????">
    <title lang="ja">????!????????? (?)</title>
  </programme>
  <programme start="20170521160000 +0900" stop="20170521163000 +0900" channel="CS218 ???????">
    <title lang="ja">???? ???????? ??? ?????? (?)</title>
    <credits>
      <actor>??????????????????????????????????
??:???????:????
1959?30?</actor>
    </credits>
  </programme>
  <programme start="20170521163000 +0900" stop="20170521170000 +0900" channel="CS218 ???????">
    <title lang="ja">???? ???????? ??? ????? (?)</title>
    <credits>
      <actor>??????????????
??:???????:????
1959?30?</actor>
    </credits>
  </programme>
  <programme start="20170521170000 +0900" stop="20170521173000 +0900" channel="CS218 ???????">
    <title lang="ja">???? ??????? ??? ????? (?)</title>
    <credits>
      <actor>?????????????????????????????????
??:???????:????
1959?</actor>
    </credits>
  </programme>
  <programme start="20170521173000 +0900" stop="20170521180000 +0900" channel="CS218 ???????">
    <title lang="ja">???? ??????? ??? ?????? (?)</title>
    <credits>
      <actor>?????????????????????????????????
??:???????:????
1959?30?</actor>
    </credits>
  </programme>
  <programme start="20170521180000 +0900" stop="20170521183000 +0900" channel="CS218 ???????">
    <title lang="ja">[?]???????????? (?)</title>
  </programme>
  <programme start="20170521183000 +0900" stop="20170521200000 +0900" channel="CS218 ???????">
    <title lang="ja">??????????? (?)</title>
    <credits>
      <actor>????????????????????????????
??:??????:????
1962?87?</actor>
    </credits>
  </programme>
  <programme start="20170521200000 +0900" stop="20170521220000 +0900" channel="CS218 ???????">
    <title lang="ja">???????? (?)</title>
  </programme>
  <programme start="20170521081500 +0900" stop="20170521101500 +0900" channel="CS219 ????">
    <title lang="ja">[?]?????? ????????????????????? (?)</title>
  </programme>
  <programme start="20170521101500 +0900" stop="20170521114500 +0900" channel="CS219 ????">
    <title lang="ja">?????? ???????????? (?)</title>
  </programme>
  <programme start="20170521114500 +0900" stop="20170521131500 +0900" channel="CS219 ????">
    <title lang="ja">?????? ???????????? (?)</title>
  </programme>
  <programme start="20170521131500 +0900" stop="20170521133000 +0900" channel="CS219 ????">
    <title lang="ja">[?]??????52 (?)</title>
  </programme>
  <programme start="20170521133000 +0900" stop="20170521144500 +0900" channel="CS219 ????">
    <title lang="ja">[?][?]?????????25?26????????????????? (?)</title>
  </programme>
  <programme start="20170521144500 +0900" stop="20170521160000 +0900" channel="CS219 ????">
    <title lang="ja">[?][?]?????????27?28????????????????? (?)</title>
  </programme>
  <programme start="20170521160000 +0900" stop="20170521183000 +0900" channel="CS219 ????">
    <title lang="ja">?????????????????????????????????? (?)</title>
  </programme>
  <programme start="20170521183000 +0900" stop="20170521184500 +0900" channel="CS219 ????">
    <title lang="ja">[?]?????? (?)</title>
  </programme>
  <programme start="20170521184500 +0900" stop="20170521210000 +0900" channel="CS219 ????">
    <title lang="ja">??????PG12???????? (?)</title>
  </programme>
  <programme start="20170521210000 +0900" stop="20170521230000 +0900" channel="CS219 ????">
    <title lang="ja">?????????????????? (?)</title>
  </programme>
  <programme start="20170521100000 +0900" stop="20170521120000 +0900" channel="CS223 ????????NECO">
    <title lang="ja">[?]?? #21.22 (?)</title>
  </programme>
  <programme start="20170521120000 +0900" stop="20170521140000 +0900" channel="CS223 ????????NECO">
    <title lang="ja">???????2????????????????? (?)</title>
  </programme>
  <programme start="20170521140000 +0900" stop="20170521160000 +0900" channel="CS223 ????????NECO">
    <title lang="ja">??????????????????????????????????? (?)</title>
  </programme>
  <programme start="20170521160000 +0900" stop="20170521182500 +0900" channel="CS223 ????????NECO">
    <title lang="ja">?????? (?)</title>
  </programme>
  <programme start="20170521182500 +0900" stop="20170521183000 +0900" channel="CS223 ????????NECO">
    <title lang="ja">??????????????????? (?)</title>
  </programme>
  <programme start="20170521183000 +0900" stop="20170521203000 +0900" channel="CS223 ????????NECO">
    <title lang="ja">?????????????????????????????????????? (?)</title>
  </programme>
  <programme start="20170521203000 +0900" stop="20170521230000 +0900" channel="CS223 ????????NECO">
    <title lang="ja">????????????????????? (?)</title>
  </programme>
  <programme start="20170521100000 +0900" stop="20170521114500 +0900" channel="CS227 ?????">
    <title lang="ja">??????????????? (?)</title>
    <country>????</country>
  </programme>
  <programme start="20170521114500 +0900" stop="20170521134500 +0900" channel="CS227 ?????">
    <title lang="ja">???????????? (?)</title>
    <country>????</country>
  </programme>
  <programme start="20170521134500 +0900" stop="20170521153000 +0900" channel="CS227 ?????">
    <title lang="ja">???? (?)</title>
    <country>????</country>
  </programme>
  <programme start="20170521153000 +0900" stop="20170521171500 +0900" channel="CS227 ?????">
    <title lang="ja">????? (?)</title>
    <country>????</country>
  </programme>
  <programme start="20170521171500 +0900" stop="20170521190000 +0900" channel="CS227 ?????">
    <title lang="ja">??????-??- (?)</title>
    <country>????</country>
  </programme>
  <programme start="20170521190000 +0900" stop="20170521205500 +0900" channel="CS227 ?????">
    <title lang="ja">?.?.???????????? (?)</title>
    <country>????</country>
  </programme>
  <programme start="20170521205500 +0900" stop="20170521210000 +0900" channel="CS227 ?????">
    <title lang="ja">???????????????? (?)</title>
  </programme>
  <programme start="20170521210000 +0900" stop="20170521230000 +0900" channel="CS227 ?????">
    <title lang="ja">?????????????????? (?)</title>
    <country>????</country>
  </programme>
  <programme start="20170521090000 +0900" stop="20170521121500 +0900" channel="CS240 ???????HD">
    <title lang="ja">??????????????? (?)</title>
    <country>????</country>
  </programme>
  <programme start="20170521121500 +0900" stop="20170521144500 +0900" channel="CS240 ???????HD">
    <title lang="ja">????? ?????????????????????????????? (?)</title>
    <country>????????????</country>
  </programme>
  <programme start="20170521144500 +0900" stop="20170521145000 +0900" channel="CS240 ???????HD">
    <title lang="ja">??????? (?)</title>
  </programme>
  <programme start="20170521145000 +0900" stop="20170521164500 +0900" channel="CS240 ???????HD">
    <title lang="ja">???????????? (?)</title>
    <country>???????????????</country>
  </programme>
  <programme start="20170521164500 +0900" stop="20170521190000 +0900" channel="CS240 ???????HD">
    <title lang="ja">????????????? (?)</title>
    <country>????</country>
  </programme>
  <programme start="20170521190000 +0900" stop="20170521210000 +0900" channel="CS240 ???????HD">
    <title lang="ja">???????????? (?)</title>
    <country>????????</country>
  </programme>
  <programme start="20170521210000 +0900" stop="20170521231500 +0900" channel="CS240 ???????HD">
    <title lang="ja">???????? (?)</title>
    <country>?????????</country>
  </programme>
  <programme start="20170521100000 +0900" stop="20170521120000 +0900" channel="BS252 ?????????">
    <title lang="ja">[?]????? (?)</title>
    <country>????</country>
  </programme>
  <programme start="20170521120000 +0900" stop="20170521140000 +0900" channel="BS252 ?????????">
    <title lang="ja">[?]???????????? (?)</title>
    <country>???</country>
  </programme>
  <programme start="20170521140000 +0900" stop="20170521160000 +0900" channel="BS252 ?????????">
    <title lang="ja">?5.1?[?]16???? (?)</title>
    <country>????</country>
  </programme>
  <programme start="20170521160000 +0900" stop="20170521190000 +0900" channel="BS252 ?????????">
    <title lang="ja">?5.1?[?]???????? (?)</title>
    <country>?????????</country>
  </programme>
  <programme start="20170521190000 +0900" stop="20170521210000 +0900" channel="BS252 ?????????">
    <title lang="ja">[?]?????????????????????? (?)</title>
    <country>?????????</country>
  </programme>
  <programme start="20170521210000 +0900" stop="20170521233000 +0900" channel="BS252 ?????????">
    <title lang="ja">?5.1?[?]??????? (?)</title>
    <country>????</country>
  </programme>
  <programme start="20170521090000 +0900" stop="20170521110500 +0900" channel="BS255 ?????????????">
    <title lang="ja">???????????????????????????? (?)</title>
  </programme>
  <programme start="20170521110500 +0900" stop="20170521113500 +0900" channel="BS255 ?????????????">
    <title lang="ja">????????????????? (?)</title>
  </programme>
  <programme start="20170521113500 +0900" stop="20170521135000 +0900" channel="BS255 ?????????????">
    <title lang="ja">RAILWAYS?49??????????????????????????? (?)</title>
  </programme>
  <programme start="20170521135000 +0900" stop="20170521140000 +0900" channel="BS255 ?????????????">
    <title lang="ja">????5????????2??????????????????????????? (?)</title>
  </programme>
  <programme start="20170521140000 +0900" stop="20170521160500 +0900" channel="BS255 ?????????????">
    <title lang="ja">???? THE MOVIE????????????????????? (?)</title>
  </programme>
  <programme start="20170521160500 +0900" stop="20170521161500 +0900" channel="BS255 ?????????????">
    <title lang="ja">????5????????2??????????????????????????? (?)</title>
  </programme>
  <programme start="20170521161500 +0900" stop="20170521184500 +0900" channel="BS255 ?????????????">
    <title lang="ja">??????? KON-SHIN????????????????????? (?)</title>
  </programme>
  <programme start="20170521184500 +0900" stop="20170521210000 +0900" channel="BS255 ?????????????">
    <title lang="ja">??????????????????????????????????? (?)</title>
  </programme>
  <programme start="20170521210000 +0900" stop="20170521231500 +0900" channel="BS255 ?????????????">
    <title lang="ja">?????????????????????????????? (?)</title>
  </programme>
  <programme start="20170521093000 +0900" stop="20170521120000 +0900" channel="BS242 J SPORTS 1">
    <title lang="ja">????????2017 ?13? ??????(??)??????(?????) (?)</title>
  </programme>
  <programme start="20170521120000 +0900" stop="20170521123000 +0900" channel="BS242 J SPORTS 1">
    <title lang="ja">[??]???????????SPEED STARS 2017 in MORIPARK Outdoor Village? (?)</title>
  </programme>
  <programme start="20170521123000 +0900" stop="20170521125000 +0900" channel="BS242 J SPORTS 1">
    <title lang="ja">[??]???? ????????????????????2017 ?? (?)</title>
  </programme>
  <programme start="20170521125000 +0900" stop="20170521150000 +0900" channel="BS242 J SPORTS 1">
    <title lang="ja">FIM ????????????2017 ?5? ???(????) (?)</title>
  </programme>
  <programme start="20170521150000 +0900" stop="20170521173000 +0900" channel="BS242 J SPORTS 1">
    <title lang="ja">B??? ???????????? ?2??/?3?? ???A?? (?)</title>
  </programme>
  <programme start="20170521173000 +0900" stop="20170521200000 +0900" channel="BS242 J SPORTS 1">
    <title lang="ja">????????2017 ?13? ??????(??)??????(?????) (?)</title>
  </programme>
  <programme start="20170521200000 +0900" stop="20170521203000 +0900" channel="BS242 J SPORTS 1">
    <title lang="ja">????????????2017 #17 ????????????? (?)</title>
  </programme>
  <programme start="20170521090000 +0900" stop="20170521110000 +0900" channel="BS243 J SPORTS 2">
    <title lang="ja">WWE ?? #1250 (?)</title>
  </programme>
  <programme start="20170521110000 +0900" stop="20170521133000 +0900" channel="BS243 J SPORTS 2">
    <title lang="ja">???? ??????? ?34?(???)-1 ???????????? (?)</title>
  </programme>
  <programme start="20170521133000 +0900" stop="20170521134500 +0900" channel="BS243 J SPORTS 2">
    <title lang="ja">[??]???? ????????????????????2017 ?? (?)</title>
  </programme>
  <programme start="20170521134500 +0900" stop="20170521135500 +0900" channel="BS243 J SPORTS 2">
    <title lang="ja">??????????2017 ???????1? ??????? (?)</title>
  </programme>
  <programme start="20170521135500 +0900" stop="20170521180000 +0900" channel="BS243 J SPORTS 2">
    <title lang="ja">[?]????2017 ?????(5/21) (?)</title>
  </programme>
  <programme start="20170521180000 +0900" stop="20170521183000 +0900" channel="BS243 J SPORTS 2">
    <title lang="ja">????????#23 (?)</title>
  </programme>
  <programme start="20170521183000 +0900" stop="20170521190000 +0900" channel="BS243 J SPORTS 2">
    <title lang="ja">???? ??????? ???????? #35 (?)</title>
  </programme>
  <programme start="20170521190000 +0900" stop="20170521220000 +0900" channel="BS243 J SPORTS 2">
    <title lang="ja">?????????2017????? ????????????????(5/20) (?)</title>
  </programme>
  <programme start="20170521220000 +0900" stop="20170521222300 +0900" channel="BS243 J SPORTS 2">
    <title lang="ja">2017 SUPER GT?????? ?2? ?????????(5/4) (?)</title>
  </programme>
  <programme start="20170521222300 +0900" stop="20170521225300 +0900" channel="BS243 J SPORTS 2">
    <title lang="ja">???? ??????? ???????? #35 (?)</title>
  </programme>
  <programme start="20170521100000 +0900" stop="20170521110000 +0900" channel="BS244 J SPORTS 3">
    <title lang="ja">???????? The REAL GIRL'S KEIRIN ???????????? (?)</title>
  </programme>
  <programme start="20170521110000 +0900" stop="20170521120000 +0900" channel="BS244 J SPORTS 3">
    <title lang="ja">WWE ??????? ????? ????????? #924 (?)</title>
  </programme>
  <programme start="20170521120000 +0900" stop="20170521150000 +0900" channel="BS244 J SPORTS 3">
    <title lang="ja">?????????2017????? ????????????????(5/20) (?)</title>
  </programme>
  <programme start="20170521150000 +0900" stop="20170521153000 +0900" channel="BS244 J SPORTS 3">
    <title lang="ja">WRC???2017 Round6 ?????????(?????) #1 (?)</title>
  </programme>
  <programme start="20170521153000 +0900" stop="20170521180000 +0900" channel="BS244 J SPORTS 3">
    <title lang="ja">?????????2017 ?????????? #1 (?)</title>
  </programme>
  <programme start="20170521180000 +0900" stop="20170521183000 +0900" channel="BS244 J SPORTS 3">
    <title lang="ja">????????????????????2017 #2 Cycle* (?)</title>
  </programme>
  <programme start="20170521183000 +0900" stop="20170521193000 +0900" channel="BS244 J SPORTS 3">
    <title lang="ja">DTM????????????? 2017 ?1? ???????(???) (?)</title>
  </programme>
  <programme start="20170521193000 +0900" stop="20170521200000 +0900" channel="BS244 J SPORTS 3">
    <title lang="ja">WRC???2017 Round6 ?????????(?????) #2 (?)</title>
  </programme>
  <programme start="20170521200000 +0900" stop="20170521220000 +0900" channel="BS244 J SPORTS 3">
    <title lang="ja">[?]WRC????????2017 R6 ??????????????????30min? (?)</title>
  </programme>
  <programme start="20170521093000 +0900" stop="20170521110000 +0900" channel="BS245 J SPORTS 4">
    <title lang="ja">???????? The REAL ???? Sogakope Dreams ???????????? (?)</title>
  </programme>
  <programme start="20170521110000 +0900" stop="20170521120000 +0900" channel="BS245 J SPORTS 4">
    <title lang="ja">GTV2017 #2 ?SUPER GT ????????? (?)</title>
  </programme>
  <programme start="20170521120000 +0900" stop="20170521133000 +0900" channel="BS245 J SPORTS 4">
    <title lang="ja">2017 SUPER GT ?3???? ?????? (?)</title>
  </programme>
  <programme start="20170521133000 +0900" stop="20170521180000 +0900" channel="BS245 J SPORTS 4">
    <title lang="ja">[?]2017 SUPER GT ?3???? ?????? (?)</title>
  </programme>
  <programme start="20170521180000 +0900" stop="20170521183000 +0900" channel="BS245 J SPORTS 4">
    <title lang="ja">???? ??????? ???????? #35 (?)</title>
  </programme>
  <programme start="20170521183000 +0900" stop="20170521190000 +0900" channel="BS245 J SPORTS 4">
    <title lang="ja">????????????????????2017 #2 Cycle* (?)</title>
  </programme>
  <programme start="20170521190000 +0900" stop="20170521213000 +0900" channel="BS245 J SPORTS 4">
    <title lang="ja">??????????????2017 ?7???? Cycle* (?)</title>
  </programme>
  <programme start="20170521213000 +0900" stop="20170521220000 +0900" channel="BS245 J SPORTS 4">
    <title lang="ja">????????????2017 #17 ????????????? (?)</title>
  </programme>
  <programme start="20170521220000 +0900" stop="20170521222300 +0900" channel="BS245 J SPORTS 4">
    <title lang="ja">[??]???? ????????????????????2017 ?? (?)</title>
  </programme>
  <programme start="20170521222300 +0900" stop="20170521225300 +0900" channel="BS245 J SPORTS 4">
    <title lang="ja">???? ??????? ???????? #35 (?)</title>
  </programme>
</tv>